supr_convertor/__init__.py
supr_convertor/config.py
supr_convertor/convertor.py
supr_convertor/data.py
supr_convertor/losses.py
supr_convertor/utils.py
supr_convertor-0.0.1.dist-info/LICENSE
supr_convertor-0.0.1.dist-info/METADATA
supr_convertor-0.0.1.dist-info/WHEEL
supr_convertor-0.0.1.dist-info/top_level.txt
supr_convertor-0.0.1.dist-info/RECORD
