Metadata-Version: 2.1
Name: supr-convertor
Version: 0.0.1
Summary: A simple tool to convert SMPL-X model parameters to SUPR model parameters.
Home-page: https://github.com/NeelayS/supr_convertor
Author: Neelay Shah
Author-email: neelay.shah@tuebingen.mpg.de
License: See LICENSE
Project-URL: Source, https://github.com/NeelayS/supr_convertor
Keywords: SMPL-X,SUPR,3D Human Body Modelling
Platform: UNKNOWN
Classifier: Natural Language :: English
Classifier: Programming Language :: Python :: 3
Requires-Python: >=3.8
Requires-Dist: fvcore (==0.1.5.post20221221)
Requires-Dist: numpy
Requires-Dist: omegaconf (==2.3.0)
Requires-Dist: scipy
Requires-Dist: setuptools (==44.0.0)
Requires-Dist: tqdm
Requires-Dist: trimesh
